QIFIAccount/QAPosition.py
QIFIAccount/QAQIFIAccount.py
QIFIAccount/QARealtimeStockSim.py
QIFIAccount/QIFIPortfolio.py
QIFIAccount/__init__.py
QIFIAccount/main.py
qifiaccount-1.15.6.dist-info/METADATA
qifiaccount-1.15.6.dist-info/WHEEL
qifiaccount-1.15.6.dist-info/entry_points.txt
qifiaccount-1.15.6.dist-info/top_level.txt
qifiaccount-1.15.6.dist-info/zip-safe
qifiaccount-1.15.6.dist-info/RECORD
